pwdPackage/__init__.py
pwdPackage/passwd.py
pwdPackage/testing.py
pwdPackage/data/names.csv
pwdPackage/data/places.csv
pwdPackage-4.1.1.dist-info/LICENSE.txt
pwdPackage-4.1.1.dist-info/METADATA
pwdPackage-4.1.1.dist-info/WHEEL
pwdPackage-4.1.1.dist-info/top_level.txt
pwdPackage-4.1.1.dist-info/RECORD
